hyvideo/__init__.py
hyvideo/commons/__init__.py
hyvideo/commons/cache_helper.py
hyvideo/commons/infer_state.py
hyvideo/commons/parallel_states.py
hyvideo/models/__init__.py
hyvideo/models/autoencoders/__init__.py
hyvideo/models/autoencoders/hunyuanvideo_15_vae.py
hyvideo/models/text_encoders/__init__.py
hyvideo/models/text_encoders/byT5/__init__.py
hyvideo/models/text_encoders/byT5/format_prompt.py
hyvideo/models/transformers/hunyuanvideo_1_5_transformer.py
hyvideo/models/transformers/modules/activation_layers.py
hyvideo/models/transformers/modules/attention.py
hyvideo/models/transformers/modules/embed_layers.py
hyvideo/models/transformers/modules/mlp_layers.py
hyvideo/models/transformers/modules/modulate_layers.py
hyvideo/models/transformers/modules/norm_layers.py
hyvideo/models/transformers/modules/posemb_layers.py
hyvideo/models/transformers/modules/ssta_attention.py
hyvideo/models/transformers/modules/token_refiner.py
hyvideo/models/transformers/modules/upsample.py
hyvideo/models/vision_encoder/__init__.py
hyvideo/optim/muon.py
hyvideo/pipelines/hunyuan_video_pipeline.py
hyvideo/pipelines/hunyuan_video_sr_pipeline.py
hyvideo/pipelines/pipeline_utils.py
hyvideo/schedulers/scheduling_flow_match_discrete.py
hyvideo/utils/communications.py
hyvideo/utils/data_utils.py
hyvideo/utils/flash_attn_no_pad.py
hyvideo/utils/infer_utils.py
hyvideo/utils/multitask_utils.py
hyvideo/utils/rewrite/clients.py
hyvideo/utils/rewrite/i2v_prompt.py
hyvideo/utils/rewrite/rewrite_utils.py
hyvideo/utils/rewrite/t2v_prompt.py
hyvideo_fork-20260122.dist-info/licenses/LICENSE
hyvideo_fork-20260122.dist-info/licenses/NOTICE
hyvideo_fork-20260122.dist-info/METADATA
hyvideo_fork-20260122.dist-info/WHEEL
hyvideo_fork-20260122.dist-info/top_level.txt
hyvideo_fork-20260122.dist-info/RECORD
