Metadata-Version: 2.4
Name: hyvideo-fork
Version: 20260122
Summary: Hunyuan Video 1.5
Requires-Python: >=3.8
License-File: LICENSE
License-File: NOTICE
Requires-Dist: tqdm>=4.67.1
Requires-Dist: torch>=2.6.0
Requires-Dist: peft>=0.17.0
Requires-Dist: openai>=2.8.0
Requires-Dist: einops>=0.8.0
Requires-Dist: loguru>=0.7.3
Requires-Dist: numpy>=1.26.4
Requires-Dist: pillow>=11.3.0
Requires-Dist: imageio>=2.37.0
Requires-Dist: angelslim>=0.2.1
Requires-Dist: imageio-ffmpeg>=0.6.0
Requires-Dist: omegaconf>=2.3.0
Requires-Dist: torchaudio>=2.6.0
Requires-Dist: diffusers>=0.35.0
Requires-Dist: safetensors>=0.5.3
Requires-Dist: torchvision>=0.21.0
Requires-Dist: qwen-vl-utils>=0.0.8
Requires-Dist: huggingface-hub>=0.34.0
Requires-Dist: huggingface_hub[cli]
Requires-Dist: transformers[accelerate,tiktoken]>=4.57.1
Requires-Dist: psutil
Dynamic: license-file
